{
  "$schema": "https://developer.microsoft.com/json-schemas/fabric/item/report/definition/page/2.1.0/schema.json",
  "name": "28fef461627ed01afe6b",
  "displayName": "01_Executive_Overview",
  "displayOption": "FitToPage",
  "height": 720,
  "width": 1280,
  "objects": {
    "background": [
      {
        "properties": {
          "color": {
            "solid": {
              "color": {
                "expr": {
                  "Literal": {
                    "Value": "'#F3F5F7'"
                  }
                }
              }
            }
          }
        }
      }
    ],
    "outspace": [
      {
        "properties": {
          "color": {
            "solid": {
              "color": {
                "expr": {
                  "Literal": {
                    "Value": "'#F3F5F7'"
                  }
                }
              }
            }
          }
        }
      }
    ]
  },
  "visualInteractions": [
    {
      "source": "e70356f6ba32b304030b",
      "target": "662557dca6011e714a67",
      "type": "NoFilter"
    },
    {
      "source": "e70356f6ba32b304030b",
      "target": "e8026dd74c2014a5e1b3",
      "type": "NoFilter"
    }
  ]
}