{
  "$schema": "https://developer.microsoft.com/json-schemas/fabric/item/report/definition/visualContainer/2.10.0/schema.json",
  "name": "bf26de85877b7db854e7",
  "position": {
    "x": 818.98447776900821,
    "y": 225.579935104797,
    "z": 10000,
    "height": 479.89616767517322,
    "width": 441.10216609664121,
    "tabOrder": 10000
  },
  "visual": {
    "visualType": "clusteredColumnChart",
    "query": {
      "queryState": {
        "Category": {
          "projections": [
            {
              "field": {
                "Column": {
                  "Expression": {
                    "SourceRef": {
                      "Entity": "dim_date"
                    }
                  },
                  "Property": "year_month"
                }
              },
              "queryRef": "dim_date.year_month",
              "nativeQueryRef": "year_month",
              "active": true
            }
          ]
        },
        "Tooltips": {
          "projections": [
            {
              "field": {
                "Measure": {
                  "Expression": {
                    "SourceRef": {
                      "Entity": "_Measures"
                    }
                  },
                  "Property": "Actual Cost by Target Month"
                }
              },
              "queryRef": "_Measures.Actual Cost by Target Month",
              "nativeQueryRef": "Actual Cost by Target Month"
            }
          ]
        },
        "Y": {
          "projections": [
            {
              "field": {
                "Measure": {
                  "Expression": {
                    "SourceRef": {
                      "Entity": "_Measures"
                    }
                  },
                  "Property": "Forecast Error by Target Month"
                }
              },
              "queryRef": "_Measures.Forecast Error by Target Month",
              "nativeQueryRef": "Forecast Error by Target Month"
            }
          ]
        }
      },
      "sortDefinition": {
        "sort": [
          {
            "field": {
              "Measure": {
                "Expression": {
                  "SourceRef": {
                    "Entity": "_Measures"
                  }
                },
                "Property": "Forecast Error by Target Month"
              }
            },
            "direction": "Descending"
          }
        ],
        "isDefaultSort": true
      }
    },
    "objects": {
      "labels": [
        {
          "properties": {
            "show": {
              "expr": {
                "Literal": {
                  "Value": "true"
                }
              }
            },
            "labelPrecision": {
              "expr": {
                "Literal": {
                  "Value": "1L"
                }
              }
            }
          }
        }
      ],
      "valueAxis": [
        {
          "properties": {
            "showAxisTitle": {
              "expr": {
                "Literal": {
                  "Value": "false"
                }
              }
            }
          }
        }
      ],
      "categoryAxis": [
        {
          "properties": {
            "showAxisTitle": {
              "expr": {
                "Literal": {
                  "Value": "false"
                }
              }
            }
          }
        }
      ],
      "legend": [
        {
          "properties": {
            "showTitle": {
              "expr": {
                "Literal": {
                  "Value": "false"
                }
              }
            }
          }
        }
      ],
      "dataPoint": [
        {
          "properties": {
            "fill": {
              "solid": {
                "color": {
                  "expr": {
                    "Measure": {
                      "Expression": {
                        "SourceRef": {
                          "Entity": "_Measures"
                        }
                      },
                      "Property": "Forecast Error Month Color"
                    }
                  }
                }
              }
            }
          },
          "selector": {
            "data": [
              {
                "dataViewWildcard": {
                  "matchingOption": 1
                }
              }
            ]
          }
        }
      ]
    },
    "visualContainerObjects": {
      "title": [
        {
          "properties": {
            "text": {
              "expr": {
                "Literal": {
                  "Value": "'Monthly forecast error across all actualized versions'"
                }
              }
            },
            "show": {
              "expr": {
                "Literal": {
                  "Value": "true"
                }
              }
            },
            "fontFamily": {
              "expr": {
                "Literal": {
                  "Value": "'''Segoe UI Semibold'', wf_segoe-ui_semibold, helvetica, arial, sans-serif'"
                }
              }
            },
            "fontSize": {
              "expr": {
                "Literal": {
                  "Value": "12D"
                }
              }
            }
          }
        }
      ]
    },
    "drillFilterOtherVisuals": true
  },
  "filterConfig": {
    "filters": [
      {
        "name": "25dee891aead2825611a",
        "field": {
          "Measure": {
            "Expression": {
              "SourceRef": {
                "Entity": "_Measures"
              }
            },
            "Property": "Actual Cost by Target Month"
          }
        },
        "type": "Advanced"
      },
      {
        "name": "6e2dff53247dc30b0a74",
        "field": {
          "Column": {
            "Expression": {
              "SourceRef": {
                "Entity": "dim_date"
              }
            },
            "Property": "year_month"
          }
        },
        "type": "Categorical"
      }
    ]
  }
}